hiyori/__init__.py
hiyori/_version.py
hiyori/bodies.py
hiyori/connection.py
hiyori/constants.py
hiyori/exceptions.py
hiyori/http_client.py
hiyori/messages.py
hiyori/multipart.py
hiyori/py.typed
hiyori/resolvers/__init__.py
hiyori/resolvers/async_.py
hiyori/resolvers/base.py
hiyori/resolvers/hosts.py
hiyori/resolvers/https.py
hiyori/resolvers/system.py
hiyori-0.2.1.dist-info/LICENSE
hiyori-0.2.1.dist-info/WHEEL
hiyori-0.2.1.dist-info/METADATA
hiyori-0.2.1.dist-info/RECORD
