Metadata-Version: 2.1
Name: hiyori
Version: 0.2.1
Summary: Hiyori is an http client for asyncio.
Home-page: https://github.com/futursolo/hiyori
License: Apache-2.0
Author: Kaede Hoshikawa
Author-email: futursolo@icloud.com
Requires-Python: >=3.6.1,<4.0.0
Classifier: License :: OSI Approved :: Apache Software License
Classifier: Operating System :: MacOS
Classifier: Operating System :: MacOS :: MacOS X
Classifier: Operating System :: Microsoft
Classifier: Operating System :: Microsoft :: Windows
Classifier: Operating System :: POSIX
Classifier: Operating System :: POSIX :: Linux
Classifier: Operating System :: Unix
Classifier: Programming Language :: Python
Classifier: Programming Language :: Python :: 3
Classifier: Programming Language :: Python :: 3 :: Only
Classifier: Programming Language :: Python :: 3.7
Classifier: Programming Language :: Python :: 3.8
Classifier: Programming Language :: Python :: 3.9
Classifier: Programming Language :: Python :: Implementation :: CPython
Provides-Extra: aiodns
Requires-Dist: aiodns (>=2.0.0,<3.0.0); extra == "aiodns"
Requires-Dist: importlib-metadata (>=4.0.1,<5.0.0); python_version <= "3.7"
Requires-Dist: magicdict (>=1.0.6,<2.0.0)
Requires-Dist: magichttp (>=1.1.1,<2.0.0)
Project-URL: Repository, https://github.com/futursolo/hiyori
